irisml/tasks/append_to_str_list.py
irisml/tasks/assertion.py
irisml/tasks/assign_class_to_strings.py
irisml/tasks/average_state_dict.py
irisml/tasks/branch.py
irisml/tasks/calculate_cosine_similarity.py
irisml/tasks/check_model_parameters.py
irisml/tasks/compare_ints.py
irisml/tasks/convert_detection_to_multilabel.py
irisml/tasks/convert_string_to_string_list.py
irisml/tasks/decode_bytes_to_str.py
irisml/tasks/decode_json_str.py
irisml/tasks/decode_json_strs.py
irisml/tasks/deserialize_tensor.py
irisml/tasks/divide_float.py
irisml/tasks/download_azure_blob.py
irisml/tasks/emulate_fp8_quantization.py
irisml/tasks/extract_image_bytes_from_dataset.py
irisml/tasks/get_array_indices_from_values.py
irisml/tasks/get_current_time.py
irisml/tasks/get_dataset_split.py
irisml/tasks/get_dataset_stats.py
irisml/tasks/get_dataset_subset.py
irisml/tasks/get_fake_image_classification_dataset.py
irisml/tasks/get_fake_image_classification_multilabel_dataset.py
irisml/tasks/get_fake_image_text_classification_dataset.py
irisml/tasks/get_fake_object_detection_dataset.py
irisml/tasks/get_fake_phrase_grounding_dataset.py
irisml/tasks/get_fake_visual_question_answering_dataset.py
irisml/tasks/get_int_from_json_strings.py
irisml/tasks/get_int_list_from_json_strings.py
irisml/tasks/get_item.py
irisml/tasks/get_key_and_int_list_from_json_string.py
irisml/tasks/get_kfold_cross_validation_dataset.py
irisml/tasks/get_secret_from_azure_keyvault.py
irisml/tasks/get_system_prompt_from_key_value_pair_schema.py
irisml/tasks/get_topk.py
irisml/tasks/if_else.py
irisml/tasks/join_filepath.py
irisml/tasks/join_two_strings.py
irisml/tasks/load_coco_detections.py
irisml/tasks/load_float_tensor_jsonl.py
irisml/tasks/load_state_dict.py
irisml/tasks/load_str_list_jsonl.py
irisml/tasks/load_strs_from_json_file.py
irisml/tasks/load_strs_from_text_file.py
irisml/tasks/load_tensor_list.py
irisml/tasks/make_cached_dataset.py
irisml/tasks/make_list.py
irisml/tasks/make_prompt_for_each_string.py
irisml_tasks-0.0.62.dist-info/LICENSE
irisml_tasks-0.0.62.dist-info/METADATA
irisml_tasks-0.0.62.dist-info/WHEEL
irisml_tasks-0.0.62.dist-info/top_level.txt
irisml_tasks-0.0.62.dist-info/RECORD
