Metadata-Version: 2.1
Name: irisml-tasks
Version: 0.0.62
Summary: Standard tasks for IrisML
Home-page: https://github.com/microsoft/irisml-tasks
Author: irisdev
License: MIT
Requires-Python: >=3.8
License-File: LICENSE
Requires-Dist: irisml
Requires-Dist: azure-identity
Requires-Dist: azure-keyvault-secrets
Requires-Dist: azure-storage-blob
Requires-Dist: Pillow
Requires-Dist: tenacity
